snmp_agent/__init__.py
snmp_agent/server.py
snmp_agent/snmp.py
snmp_agent/utils.py
snmp_agent-0.2.2.dist-info/LICENSE
snmp_agent-0.2.2.dist-info/WHEEL
snmp_agent-0.2.2.dist-info/METADATA
snmp_agent-0.2.2.dist-info/RECORD
